photocard/__init__.py
photocard/__main__.py
photocard/photocard.py
photocard-0.1.2.dist-info/LICENSE
photocard-0.1.2.dist-info/METADATA
photocard-0.1.2.dist-info/WHEEL
photocard-0.1.2.dist-info/RECORD
