Metadata-Version: 2.1
Name: photocard
Version: 0.1.2
Summary: A Pythonic interface for TfL's Photocard service
Home-page: https://pypi.org/project/photocard/
License: MIT
Author: Oskar
Author-email: 56176746+OskarZyg@users.noreply.github.com
Requires-Python: >=3.10,<4.0
Classifier: License :: OSI Approved :: MIT License
Classifier: Programming Language :: Python :: 3
Classifier: Programming Language :: Python :: 3.10
Classifier: Programming Language :: Python :: 3.11
Requires-Dist: urllib3 (>=1.26.15,<2.0.0)
Project-URL: Repository, https://github.com/oskarzyg/photocard/
